bashimu.py
bashimu-1.2.1.dist-info/licenses/LICENSE
bashimu-1.2.1.dist-info/METADATA
bashimu-1.2.1.dist-info/WHEEL
bashimu-1.2.1.dist-info/entry_points.txt
bashimu-1.2.1.dist-info/top_level.txt
bashimu-1.2.1.dist-info/RECORD
