Metadata-Version: 2.4
Name: bashimu
Version: 1.2.1
Summary: A command-line tool to interact with LLMs for bash and Linux questions
Home-page: https://github.com/wiktorjl/bashimu
Author: Wiktor Lukasik
License: MIT
Project-URL: Homepage, https://github.com/wiktorjl/bashimu
Project-URL: Bug Tracker, https://github.com/wiktorjl/bashimu/issues
Project-URL: Source Code, https://github.com/wiktorjl/bashimu
Keywords: bash,linux,cli,chatgpt,openai,llm,terminal
Classifier: Programming Language :: Python :: 3
Classifier: Programming Language :: Python :: 3.7
Classifier: Programming Language :: Python :: 3.8
Classifier: Programming Language :: Python :: 3.9
Classifier: Programming Language :: Python :: 3.10
Classifier: Programming Language :: Python :: 3.11
Classifier: License :: OSI Approved :: MIT License
Classifier: Operating System :: OS Independent
Classifier: Environment :: Console
Classifier: Intended Audience :: Developers
Classifier: Intended Audience :: System Administrators
Classifier: Topic :: Software Development :: Libraries :: Python Modules
Classifier: Topic :: System :: Systems Administration
Classifier: Topic :: Utilities
Requires-Python: >=3.7
License-File: LICENSE
Requires-Dist: prompt_toolkit
Requires-Dist: openai
Requires-Dist: requests
Requires-Dist: rich
Dynamic: home-page
Dynamic: license-file
Dynamic: requires-python
